bugboy/__init__.py
bugboy/logger.py
bugboy-0.0.2.dist-info/licenses/LICENSE
bugboy-0.0.2.dist-info/METADATA
bugboy-0.0.2.dist-info/WHEEL
bugboy-0.0.2.dist-info/top_level.txt
bugboy-0.0.2.dist-info/RECORD
