Metadata-Version: 2.4
Name: bugboy
Version: 0.0.2
Summary: Simple logger helper
Author: Tarun (Guddu)
Requires-Python: >=3.8
License-File: LICENSE
Dynamic: license-file
